zisraw.py
zisraw-2018.10.18.dist-info/LICENSE
zisraw-2018.10.18.dist-info/METADATA
zisraw-2018.10.18.dist-info/WHEEL
zisraw-2018.10.18.dist-info/top_level.txt
zisraw-2018.10.18.dist-info/RECORD
